Workbook
Name birth1: '[1]Admin Population'!$C$16
Name hrs_supervision_after_first_yr: '[1]Admin Training & supervision'!$H$5
Name MMR: '[1]Admin Population'!$C$12
Name no_screened_pos_midwives_AN: '[1]Admin Population'!$C$40
Name No_visits_antenatal_period: '[1]Admin Screening & treatment'!$C$6
Name Probability_of_still_birth: '[1]Admin Population'!$C$11
Name prop_accept_treatment: '[1]Admin Population'!$C$63
Name prop_access_clinics_AN: '[1]Admin Population'!$C$23
Name prop_screened_pos_year_1_AN: '[1]Admin Population'!$C$42
Name prop_screened_year_1: '[1]Admin Population'!$C$28

Sheet inputs
C1: optional | D1: must be unique | H1: only if tunable | I1: only if tunable | J1: optional
B2: Section | C2: Subsection | D2: Variable name | E2: Default Value | F2: Is Tunable By User? | G2: Step Size | H2: Min range | I2: Max range | J2: Unit | K2: Text input | L2: Display name | M2: Tooltip | N2: Comments (note on the value, source of the default, etc.)
B3: Mothers' impact | C3: Cohort | D3: Live births | E3: 645273 | F3: Yes | G3: 1 | H3: 0 | I3: 60000000 | J3: Number | K3: Yes | L3: Live births | M3: insert tooltip here | N3: e.g., Calculated by muliplying birth rate w population
B4: Mothers' impact | C4: Cohort | D4: Still birth rate (per 1,000) | E4: 3.9 | F4: Yes | G4: 0.1 | H4: 0 | I4: 20 | J4: Rate | K4: No | L4: Still birth rate (per 1,000) | M4: insert tooltip here
B5: Mothers' impact | C5: Cohort | D5: Mortality probability during / after birth | E5: 0.0003 | F5: Yes | G5: 1e-05 | H5: 0 | I5: 0.1 | J5: Probability | K5: Yes | L5: Mortality probability during / after birth | M5: insert tooltip here
B6: Mothers' impact | C6: Cohort | D6: Mortality probability (women aged 15 to 39yrs) | E6: 0.0007 | F6: Yes | G6: 1e-05 | H6: 0 | I6: 0.1 | J6: Probability | K6: Yes | L6: Mortality probability (women aged 15 to 39yrs) | M6: insert tooltip here
B7: Mothers' impact | C7: With antenatal mental health problems | D7: Prevalence / probability antenatal depression (moderate and severe only) | E7: 0.2 | F7: Yes | G7: 0.1 | H7: 0 | I7: 100 | J7: Percentage | K7: No | L7: Prevalence antenatal depression (moderate or severe) | M7: insert tooltip here
B8: Mothers' impact | C8: With antenatal mental health problems | D8: Proportion of antenatal depression that is moderate depression | E8: 0.8 | F8: No | J8: Percentage | K8: No | L8: Proportion of antenatal depression that is moderate depression | M8: insert tooltip here
B9: Mothers' impact | C9: With antenatal mental health problems | D9: Proportion of antenatal depression that is severe depression | E9: 0.2 | F9: No | J9: Percentage | K9: No | L9: Proportion of antenatal depression that is severe depression | M9: insert tooltip here
B10: Mothers' impact | C10: With antenatal mental health problems | D10: Prevalence / probability antenatal anxiety (any) without depression | E10: 0.035 | F10: Yes | G10: 0.1 | H10: 0 | I10: 100 | J10: Percentage | K10: No | L10: Prevalence antenatal anxiety without depression | M10: insert tooltip here
B11: Mothers' impact | C11: With postnatal mental health problems | D11: Prevalence postnatal depression (moderate or severe) | E11: 0.2 | F11: Yes | G11: 0.1 | H11: 0 | I11: 100 | J11: Percentage | K11: No | L11: Prevalence postnatal depression (moderate or severe) | M11: insert tooltip here
B12: Mothers' impact | C12: With postnatal mental health problems | D12: Proportion of postnatal depression that is moderate depression | E12: 0.8 | F12: No | J12: Percentage | K12: No | L12: Proportion of postnatal depression that is moderate depression | M12: insert tooltip here
B13: Mothers' impact | C13: With postnatal mental health problems | D13: Proportion of postnatal depression that is severe depression | E13: 0.2 | F13: No | J13: Percentage | K13: No | L13: Proportion of postnatal depression that is severe depression | M13: insert tooltip here
B14: Mothers' impact | C14: With postnatal mental health problems | D14: Prevalence / probability postnatal anxiety (any) without depression | E14: 0.1 | F14: Yes | G14: 0.1 | H14: 0 | I14: 100 | J14: Percentage | K14: No | L14: Prevalence postnatal anxiety without depression | M14: insert tooltip here
B15: Mothers' impact | C15: With ongoing mental health problems | D15: Prevalence / probability ongoing depression | E15: 0.05 | F15: No | J15: Percentage | K15: No | L15: Prevalence ongoing depression | M15: insert tooltip here
B16: Mothers' impact | C16: With ongoing mental health problems | D16: Prevalence / probability ongoing anxiety | E16: 0.05 | F16: No | J16: Percentage | K16: No | L16: Prevalence ongoing anxiety | M16: insert tooltip here
B17: Mothers' impact | C17: With ongoing mental health problems | D17: Duration of perinatal mental health problems | E17: 0.25 | F17: No | J17: Yrs | K17: No | L17: Duration of perinatal mental health problems | M17: insert tooltip here
B18: Mothers' impact | C18: Disability Adjusted Life Years | D18: Disability weight for moderate depression | E18: 0.396 | F18: No | J18: Weight | K18: No | L18: Disability weight for moderate depression | M18: insert tooltip here
B19: Mothers' impact | C19: Disability Adjusted Life Years | D19: Disability weight for severe depression | E19: 0.658 | F19: No | J19: Weight | K19: No | L19: Disability weight for severe depression | M19: insert tooltip here
B20: Mothers' impact | C20: Disability Adjusted Life Years | D20: Disability weight for moderate anxiety | E20: 0.133 | F20: No | J20: Weight | K20: No | L20: Disability weight for moderate anxiety | M20: insert tooltip here
B21: Mothers' impact | C21: Quality Adjusted Life Years | D21: Health utility weight for moderate depression | E21: =1-E18 -> 0.604 | F21: No | J21: Weight | K21: No | L21: Health utility weight for moderate depression | M21: insert tooltip here
B22: Mothers' impact | C22: Quality Adjusted Life Years | D22: Health utility weight for severe depression | E22: =1-E19 -> 0.342 | F22: No | J22: Weight | K22: No | L22: Health utility weight for severe depression | M22: insert tooltip here
B23: Mothers' impact | C23: Quality Adjusted Life Years | D23: Health utility weight for moderate anxiety | E23: =1-E22 -> 0.658 | F23: No | J23: Weight | K23: No | L23: Health utility weight for moderate anxiety | M23: insert tooltip here
B24: Mothers' impact | C24: Years of Life Lost | D24: Suicide rate ante- and postnatal period (per 100,000) | E24: 5.5 | F24: Yes | G24: 0.1 | H24: 0 | I24: 20 | J24: Rate | K24: No | L24: Suicide rate ante- and postnatal period (per 100,000) | M24: insert tooltip here
B25: Mothers' impact | C25: Years of Life Lost | D25: Years of Life Lost due to suicide | E25: 60 | F25: No | J25: Yrs | K25: No | L25: Years of Life Lost due to suicide | M25: insert tooltip here
B26: Mothers' impact | C26: Valuing quality of life loss, in USD | D26: GDP per capita | E26: 7172 | F26: Yes | G26: 1 | H26: 0 | I26: 100000 | J26: Currency | K26: Yes | L26: GDP per capita | M26: insert tooltip here
B27: Mothers + children impact | C27: Valuing quality of life loss, in USD | D27: Weight for valuing DALY with GDP per capita | E27: 0.5 | F27: No | J27: Weight | K27: No | L27: Weight for valuing DALY with GDP per capita | M27: insert tooltip here
B28: Mothers' impact | C28: Valuing productivity loss, in USD | D28: Income decrement depression women per year, in USD | E28: 2217 | F28: Yes | G28: 1 | H28: 0 | I28: 6000 | J28: Currency | K28: Yes | L28: Income decrement depression women per year | M28: insert tooltip here
B29: Mothers' impact | C29: Valuing productivity loss, in USD | D29: Income decrement anxiety women per year, in USD | E29: 2217 | F29: Yes | G29: 1 | H29: 0 | I29: 6000 | J29: Currency | K29: Yes | L29: Income decrement anxiety women per year | M29: insert tooltip here
B30: Mothers + children impact | C30: Exchange rate | D30: Exchange rate Thai Bat USD | E30: =0.03 -> 0.03 | F30: N/A | J30: Rate | K30: No | L30: Exchange rate Thai Bat USD | M30: insert tooltip here
B31: Mothers + children impact | C31: Discounting | D31: Discount rate +1 | E31: 1.03 | F31: No | J31: Number | K31: No | L31: Discount rate +1 | M31: insert tooltip here
B32: Children's impact | C32: Mortality | D32: Mortality birth year | E32: 0.007 | F32: Yes | G32: 1e-05 | H32: 0 | I32: 0.03 | J32: Probability | K32: Yes | L32: Birth year | M32: insert tooltip here
B33: Children's impact | C33: Mortality | D33: Mortality Years 1 to 5 | E33: 0.0003 | F33: Yes | G33: 1e-05 | H33: 0 | I33: 0.03 | J33: Probability | K33: Yes | L33: Years 1 to 5 | M33: insert tooltip here
B34: Children's impact | C34: Mortality | D34: Mortality Years 6 to 10 | E34: 0.0003 | F34: Yes | G34: 1e-05 | H34: 0 | I34: 0.03 | J34: Probability | K34: Yes | L34: Years 6 to 10 | M34: insert tooltip here
B35: Children's impact | C35: Mortality | D35: Mortality Years 11 to 20 | E35: 0.0003 | F35: Yes | G35: 1e-05 | H35: 0 | I35: 0.03 | J35: Probability | K35: Yes | L35: Years 11 to 20 | M35: insert tooltip here
B36: Children's impact | C36: Mortality | D36: Mortality Years 21 to 25 | E36: 0.001 | F36: Yes | G36: 1e-05 | H36: 0 | I36: 0.03 | J36: Probability | K36: Yes | L36: Years 21 to 25 | M36: insert tooltip here
B37: Children's impact | C37: Mortality | D37: Mortality Years 26 to 30 | E37: 0.002 | F37: Yes | G37: 1e-05 | H37: 0 | I37: 0.03 | J37: Probability | K37: Yes | L37: Years 26 to 30 | M37: insert tooltip here
B38: Children's impact | C38: Mortality | D38: Mortality Years 31 to 40 | E38: 0.002 | F38: Yes | G38: 1e-05 | H38: 0 | I38: 0.03 | J38: Probability | K38: Yes | L38: Years 31 to 40 | M38: insert tooltip here
B39: Children's impact | C39: Exposure | D39: Prevalence of perinatal mental health condition impacting on child outcome 1 PRTB | E39: 0.2 | F39: No | J39: Probability | K39: No | L39: Prevalence of perinatal mental health condition impacting on child outcome 1 PRTB | M39: insert tooltip here | N39: PRTB = pre-term birth
B40: Children's impact | C40: Exposure | D40: Prevalence of perinatal mental health condition impacting on child outcome 2 LBW | E40: 0.2 | F40: No | J40: Probability | K40: No | L40: Prevalence of perinatal mental health condition impacting on child outcome 2 LBW | M40: insert tooltip here | N40: LBW = low birth weight
B41: Children's impact | C41: Exposure | D41: Prevalence of perinatal mental health condition impacting on child outcome 3 HOSP | E41: 0.2 | F41: No | J41: Probability | K41: No | L41: Prevalence of perinatal mental health condition impacting on child outcome 3 HOSP | M41: insert tooltip here | N41: HOSP = hospitalisation
B42: Children's impact | C42: Exposure | D42: Prevalence of perinatal mental health condition impacting on child outcome 4 DIARRH | E42: 0.2 | F42: No | J42: Probability | K42: No | L42: Prevalence of perinatal mental health condition impacting on child outcome 4 DIARRH | M42: insert tooltip here | N42: DIARRH = diarrhoea
B43: Children's impact | C43: Exposure | D43: Prevalence of perinatal mental health condition impacting on child outcome 5 ASTH | E43: 0.2 | F43: No | J43: Probability | K43: No | L43: Prevalence of perinatal mental health condition impacting on child outcome 5 ASTH | M43: insert tooltip here | N43: ASTH = asthma/ severe recurring wheezing
B44: Children's impact | C44: Exposure | D44: Prevalence of perinatal mental health condition impacting on child outcome 6 LRTI | E44: 0.2 | F44: No | J44: Probability | K44: No | L44: Prevalence of perinatal mental health condition impacting on child outcome 6 LRTI | M44: insert tooltip here | N44: LRTI = lower respiratory tract infections
B45: Children's impact | C45: Exposure | D45: Prevalence of perinatal mental health condition impacting on child outcome 7 STUNT | E45: 0.2 | F45: No | J45: Probability | K45: No | L45: Prevalence of perinatal mental health condition impacting on child outcome 7 STUNT | M45: insert tooltip here | N45: STUNT = stunting
B46: Children's impact | C46: Exposure | D46: Prevalence of perinatal mental health condition impacting on child outcome 8 WAST | E46: 0.2 | F46: No | J46: Probability | K46: No | L46: Prevalence of perinatal mental health condition impacting on child outcome 8 WAST | M46: insert tooltip here | N46: WAST = wasting
B47: Children's impact | C47: Exposure | D47: Prevalence of perinatal mental health condition impacting on child outcome 9 CD | E47: 0.2 | F47: No | J47: Probability | K47: No | L47: Prevalence of perinatal mental health condition impacting on child outcome 9 CD | M47: insert tooltip here | N47: CD = conduct disorder
B48: Children's impact | C48: Exposure | D48: Prevalence of perinatal mental health condition impacting on child outcome 10 AD | E48: 0.2 | F48: No | J48: Probability | K48: No | L48: Prevalence of perinatal mental health condition impacting on child outcome 10 AD | M48: insert tooltip here | N48: AD = attention disorder
B49: Children's impact | C49: Exposure | D49: Prevalence of perinatal mental health condition impacting on child outcome 11 ED | E49: 0.2 | F49: No | J49: Probability | K49: No | L49: Prevalence of perinatal mental health condition impacting on child outcome 11 ED | M49: insert tooltip here | N49: ED = emotional disorder
B50: Children's impact | C50: Prevalence age 0-1 | D50: Outcome 1 pre-term birth | E50: 0.1 | F50: Yes | G50: 0.001 | H50: 0 | I50: 0.3 | J50: Probability | K50: No | L50: Pre-term birth | M50: insert tooltip here
B51: Children's impact | C51: Prevalence age 0-1 | D51: Outcome 2 low birth weight | E51: 0.1 | F51: Yes | G51: 0.001 | H51: 0 | I51: 0.3 | J51: Probability | K51: No | L51: Low birth weight | M51: insert tooltip here
B52: Children's impact | C52: Prevalence age 0-1 | D52: Outcome 3 hospitalisation | E52: 0.05 | F52: Yes | G52: 0.001 | H52: 0 | I52: 0.3 | J52: Probability | K52: No | L52: Hospitalisation | M52: insert tooltip here
B53: Children's impact | C53: Prevalence age 0-1 | D53: Outcome 4 diarrhoea | E53: 0.034 | F53: Yes | G53: 0.001 | H53: 0 | I53: 0.3 | J53: Probability | K53: No | L53: Diarrhoea | M53: insert tooltip here
B54: Children's impact | C54: Prevalence age 0-1 | D54: Outcome 5 asthma/ severe recurring wheezing | E54: 0.1 | F54: Yes | G54: 0.001 | H54: 0 | I54: 0.3 | J54: Probability | K54: No | L54: Asthma / severe recurring wheezing | M54: insert tooltip here
B55: Children's impact | C55: Prevalence age 0-1 | D55: Outcome 6 lower respiratory tract infections | E55: 0.05 | F55: Yes | G55: 0.001 | H55: 0 | I55: 0.3 | J55: Probability | K55: No | L55: Lower respiratory tract infections | M55: insert tooltip here
B56: Children's impact | C56: Prevalence age 1+ | D56: Outcome 7 stunting | E56: 0.124 | F56: Yes | G56: 0.001 | H56: 0 | I56: 0.3 | J56: Probability | K56: No | L56: Stunting | M56: insert tooltip here
B57: Children's impact | C57: Prevalence age 1+ | D57: Outcome 8 wasting | E57: 0.072 | F57: Yes | G57: 0.001 | H57: 0 | I57: 0.3 | J57: Probability | K57: No | L57: Wasting | M57: insert tooltip here
B58: Children's impact | C58: Prevalence age 1+ | D58: Outcome 9 conduct disorder | E58: 0.2 | F58: Yes | G58: 0.001 | H58: 0 | I58: 0.3 | J58: Probability | K58: No | L58: Conduct disorder | M58: insert tooltip here
B59: Children's impact | C59: Prevalence age 1+ | D59: Outcome 10 attention disorder | E59: 0.2 | F59: Yes | G59: 0.001 | H59: 0 | I59: 0.3 | J59: Probability | K59: No | L59: Attention disorder | M59: insert tooltip here
B60: Children's impact | C60: Prevalence age 1+ | D60: Outcome 11 emotional disorder | E60: 0.2 | F60: Yes | G60: 0.001 | H60: 0 | I60: 0.3 | J60: Probability | K60: No | L60: Emotional disorder | M60: insert tooltip here
B61: Children's impact | C61: Relative risk | D61: Outcome 1 pre-term birth | E61: 2.41 | F61: Yes | G61: 0.001 | H61: 0 | I61: 5 | J61: Relative Risk | K61: No | L61: Pre-term birth | M61: insert tooltip here | O61: *** Sam *** Changed all of these from "None" to "Relative Risk" as they were being interpreted as numbers by the code that reads in this excel file.
B62: Children's impact | C62: Relative risk | D62: Outcome 2 low birth weight | E62: 1.66 | F62: Yes | G62: 0.001 | H62: 0 | I62: 5 | J62: Relative Risk | K62: No | L62: Low birth weight | M62: insert tooltip here
B63: Children's impact | C63: Relative risk | D63: Outcome 3 hospitalisation | E63: 0 | F63: Yes | G63: 0.001 | H63: 0 | I63: 5 | J63: Relative Risk | K63: No | L63: Hospitalisation | M63: insert tooltip here
B64: Children's impact | C64: Relative risk | D64: Outcome 4 diarrhoea | E64: 0 | F64: Yes | G64: 0.001 | H64: 0 | I64: 5 | J64: Relative Risk | K64: No | L64: Diarrhoea | M64: insert tooltip here
B65: Children's impact | C65: Relative risk | D65: Outcome 5 asthma/ severe recurring wheezing | E65: 0 | F65: Yes | G65: 0.001 | H65: 0 | I65: 5 | J65: Relative Risk | K65: No | L65: Asthma/ severe recurring wheezing | M65: insert tooltip here
B66: Children's impact | C66: Relative risk | D66: Outcome 6 lower respiratory tract infections | E66: 0 | F66: Yes | G66: 0.001 | H66: 0 | I66: 5 | J66: Relative Risk | K66: No | L66: Lower respiratory tract infections | M66: insert tooltip here
B67: Children's impact | C67: Relative risk | D67: Outcome 7 stunting | E67: 1.71 | F67: Yes | G67: 0.001 | H67: 0 | I67: 5 | J67: Relative Risk | K67: No | L67: Stunting | M67: insert tooltip here
B68: Children's impact | C68: Relative risk | D68: Outcome 8 wasting | E68: 1.75 | F68: Yes | G68: 0.001 | H68: 0 | I68: 5 | J68: Relative Risk | K68: No | L68: Wasting | M68: insert tooltip here
B69: Children's impact | C69: Relative risk | D69: Outcome 9 conduct disorder | E69: 0 | F69: Yes | G69: 0.001 | H69: 0 | I69: 5 | J69: Relative Risk | K69: No | L69: Conduct disorder | M69: insert tooltip here
B70: Children's impact | C70: Relative risk | D70: Outcome 10 attention disorder | E70: 0 | F70: Yes | G70: 0.001 | H70: 0 | I70: 5 | J70: Relative Risk | K70: No | L70: Attention disorder | M70: insert tooltip here
B71: Children's impact | C71: Relative risk | D71: Outcome 11 emotional disorder | E71: 0 | F71: Yes | G71: 0.001 | H71: 0 | I71: 5 | J71: Relative Risk | K71: No | L71: Emotional disorder | M71: insert tooltip here
B72: Children's impact | C72: Disability Adjusted Life Years | D72: DALYs lifetime total outcome 2 LBW | E72: 6.8 | F72: No | J72: Yrs | K72: No | L72: DALYs lifetime total outcome 2 LBW | M72: insert tooltip here
B73: Children's impact | C73: Disability Adjusted Life Years | D73: Disability weight outcome 5 ASTH | E73: 0.036 | F73: No | J73: Weight | K73: No | L73: Disability weight outcome 5 ASTH | M73: insert tooltip here
B74: Children's impact | C74: Disability Adjusted Life Years | D74: Disability weight outcome 6 LRTI | E74: 0.133 | F74: No | J74: Weight | K74: No | L74: Disability weight outcome 6 LRTI | M74: insert tooltip here
B75: Children's impact | C75: Disability Adjusted Life Years | D75: Disability weight outcome 8 | E75: 0.128 | F75: No | J75: Weight | K75: No | L75: Disability weight outcome 8 | M75: insert tooltip here | O75: *** Sam *** edited this to say "Children Impact". Before it was just blank.
B76: Children's impact | C76: Disability Adjusted Life Years | D76: Disability weight outcome 9 | E76: 0.241 | F76: No | J76: Weight | K76: No | L76: Disability weight outcome 9 | M76: insert tooltip here
B77: Children's impact | C77: Disability Adjusted Life Years | D77: Disability weight outcome 10 | E77: 0.045 | F77: No | J77: Weight | K77: No | L77: Disability weight outcome 10 | M77: insert tooltip here
B78: Children's impact | C78: Disability Adjusted Life Years | D78: Disability weight outcome 11 | E78: 0.265 | F78: No | J78: Weight | K78: No | L78: Disability weight outcome 11 | M78: insert tooltip here
B79: Children's impact | C79: Quality Adjusted Life Years | D79: QALYs loss lifetime total outcome 2 LBW | E79: 0 | F79: No | J79: Weight | K79: No | L79: QALYs loss lifetime total outcome 2 LBW | M79: insert tooltip here | N79: we can't derive this
B80: Children's impact | C80: Quality Adjusted Life Years | D80: Health utility weight (HUW) outcome 5 ASTH | E80: =(1-E73) -> 0.964 | F80: No | J80: Weight | K80: No | L80: Health utility weight (HUW) outcome 5 ASTH | M80: insert tooltip here
B81: Children's impact | C81: Quality Adjusted Life Years | D81: Health utility weight outcome 6 LRTI | E81: =(1-E74) -> 0.867 | F81: No | J81: Weight | K81: No | L81: Health utility weight outcome 6 LRTI | M81: insert tooltip here
B82: Children's impact | C82: Quality Adjusted Life Years | D82: Health utility weight outcome 8 WAST | E82: =(1-E75) -> 0.872 | F82: No | J82: Weight | K82: No | L82: Health utility weight outcome 8 WAST | M82: insert tooltip here
B83: Children's impact | C83: Quality Adjusted Life Years | D83: Health utility weight outcome 9 CD | E83: =(1-E76) -> 0.759 | F83: No | J83: Weight | K83: No | L83: Health utility weight outcome 9 CD | M83: insert tooltip here
B84: Children's impact | C84: Quality Adjusted Life Years | D84: Health utility weight outcome 10 AD | E84: =(1-E77) -> 0.955 | F84: No | J84: Weight | K84: No | L84: Health utility weight outcome 10 AD | M84: insert tooltip here
B85: Children's impact | C85: Quality Adjusted Life Years | D85: Health utility weight outcome 11 ED | E85: =(1-E78) -> 0.735 | F85: No | J85: Weight | K85: No | L85: Health utility weight outcome 11 ED | M85: insert tooltip here
B86: Children's impact | C86: Value for quality of life loss | D86: GDP per capita (all) | E86: 4500 | F86: No | H86: 0 | I86: 100000 | J86: Currency | K86: No | L86: GDP per capita (all) | M86: insert tooltip here
B87: Children's impact | C87: Valuing productivity loss, in USD | D87: Income decrement outcomes 9 to 11 | E87: 0 | F87: Yes | G87: 1 | H87: 0 | I87: 2000 | J87: Currency | K87: Yes | L87: Income decrement: Conduct, Attention and Emotional disorders | M87: insert tooltip here
B88: Children's impact | C88: Valuing productivity loss, in USD | D88: Income decrement outcome 7 stunting | E88: 719.5 | F88: Yes | G88: 1 | H88: 0 | I88: 2000 | J88: Currency | K88: Yes | L88: Income decrement: Stunting | M88: insert tooltip here
B89: Children's impact | C89: Valuing healthcare age 0-1, in USD | D89: Outcome 1 | E89: 526 | F89: Yes | G89: 1 | H89: 0 | I89: 10000 | J89: Currency | K89: Yes | L89: Pre-term birth | M89: insert tooltip here | N89: refers to short-term costs in 1st year per average child with that problem (i.e. reflects a probabilty that child is being treated fore the problem)
B90: Children's impact | C90: Valuing healthcare age 0-1, in USD | D90: Outcome 2 | E90: 445 | F90: Yes | G90: 1 | H90: 0 | I90: 10000 | J90: Currency | K90: Yes | L90: Low birth weight | M90: insert tooltip here
B91: Children's impact | C91: Valuing healthcare age 0-1, in USD | D91: Outcome 4 | E91: 0 | F91: Yes | G91: 1 | H91: 0 | I91: 10000 | J91: Currency | K91: Yes | L91: Diarrhoea | M91: insert tooltip here
B92: Children's impact | C92: Valuing healthcare age 0-1, in USD | D92: Outcome 5 | E92: 0 | F92: Yes | G92: 1 | H92: 0 | I92: 10000 | J92: Currency | K92: Yes | L92: Asthma / severe recurring wheezing | M92: insert tooltip here
B93: Children's impact | C93: Valuing healthcare age 0-1, in USD | D93: Outcome 6 | E93: 0 | F93: Yes | G93: 1 | H93: 0 | I93: 10000 | J93: Currency | K93: Yes | L93: Lower respiratory tract infections | M93: insert tooltip here
B94: Children's impact | C94: Valuing healthcare age 0-1, in USD | D94: Outcome 7 | E94: 1193 | F94: Yes | G94: 1 | H94: 0 | I94: 10000 | J94: Currency | K94: Yes | L94: Stunting | M94: insert tooltip here
B95: Children's impact | C95: Valuing healthcare age 0-1, in USD | D95: Outcome 8 | E95: 0 | F95: Yes | G95: 1 | H95: 0 | I95: 10000 | J95: Currency | K95: Yes | L95: Wasting | M95: insert tooltip here | N95: I removed outcome acronyms from these lines to make encoding in Python easier.
B96: Children's impact | C96: Years for calculating child impact | D96: Life year 1 | E96: 1 | F96: No | J96: Year | K96: No | L96: Life year 1 | M96: insert tooltip here
B97: Children's impact | C97: Years for calculating child impact | D97: Life year 2 | E97: 2 | F97: No | J97: Year | K97: No | L97: Life year 2 | M97: insert tooltip here
B98: Children's impact | C98: Years for calculating child impact | D98: Life year 3 | E98: 3 | F98: No | J98: Year | K98: No | L98: Life year 3 | M98: insert tooltip here
B99: Children's impact | C99: Years for calculating child impact | D99: Life year 4 | E99: 4 | F99: No | J99: Year | K99: No | L99: Life year 4 | M99: insert tooltip here
B100: Children's impact | C100: Years for calculating child impact | D100: Life year 5 | E100: 5 | F100: No | J100: Year | K100: No | L100: Life year 5 | M100: insert tooltip here
...

Sheet computations
A1: Section | B1: Subsection | C1: Variable Name | D1: Formula | E1: Formula expanded
A2: Mother impact | B2: Cohort | C2: Number of women antenatal period | D2: =inputs!E3/(1 - inputs!E4/1000) -> 647799.42 | E2: =_xlfn.FORMULATEXT(D2) -> =inputs!E3/(1 - inputs!E4/1000) | F2: This formula has been edited, it is now: live births / (1 – stillbirth rate) rather than live births * (1 + stillbirth rate). This is because the stillbirths are not included in live births and so live births does not represent 100% of all births.
A3: Mother impact | B3: Cohort | C3: Number of women postnatal period | D3: =inputs!E3-inputs!E5*inputs!E3 -> 645079.42 | E3: =_xlfn.FORMULATEXT(D3) -> =inputs!E3-inputs!E5*inputs!E3
A4: Mother impact | B4: Cohort | C4: Number of women Year + 1 | D4: =D3-inputs!$E$6*computations!D3 -> 644627.86 | E4: =_xlfn.FORMULATEXT(D4) -> =D3-inputs!$E$6*computations!D3
A5: Mother impact | B5: Cohort | C5: Number of women Year + 2 | D5: =D4-inputs!$E$6*D4 -> 644176.62 | E5: =_xlfn.FORMULATEXT(D5) -> =D4-inputs!$E$6*D4
A6: Mother impact | B6: Cohort | C6: Number of women Year + 3 | D6: =D5-inputs!$E$6*D5 -> 643725.7 | E6: =_xlfn.FORMULATEXT(D6) -> =D5-inputs!$E$6*D5
A7: Mother impact | B7: Cohort | C7: Number of women Year + 4 | D7: =D6-inputs!$E$6*D6 -> 643275.09 | E7: =_xlfn.FORMULATEXT(D7) -> =D6-inputs!$E$6*D6
A8: Mother impact | B8: Cohort | C8: Number of women Year + 5 | D8: =D7-inputs!$E$6*D7 -> 642824.8 | E8: =_xlfn.FORMULATEXT(D8) -> =D7-inputs!$E$6*D7
A9: Mother impact | B9: Cohort | C9: Number of women Year + 6 | D9: =D8-inputs!$E$6*D8 -> 642374.82 | E9: =_xlfn.FORMULATEXT(D9) -> =D8-inputs!$E$6*D8
A10: Mother impact | B10: Cohort | C10: Number of women Year + 7 | D10: =D9-inputs!$E$6*D9 -> 641925.16 | E10: =_xlfn.FORMULATEXT(D10) -> =D9-inputs!$E$6*D9
A11: Mother impact | B11: Cohort | C11: Number of women Year + 8 | D11: =D10-inputs!$E$6*D10 -> 641475.81 | E11: =_xlfn.FORMULATEXT(D11) -> =D10-inputs!$E$6*D10
A12: Mother impact | B12: Cohort | C12: Number of women Year + 9 | D12: =D11-inputs!$E$6*D11 -> 641026.78 | E12: =_xlfn.FORMULATEXT(D12) -> =D11-inputs!$E$6*D11
A13: Mother impact | B13: Cohort | C13: Number of women Year + 10 | D13: =D12-inputs!$E$6*D12 -> 640578.06 | E13: =_xlfn.FORMULATEXT(D13) -> =D12-inputs!$E$6*D12
A14: Mother impact | B14: Women with moderate depression | C14: Number women moderately depressed antenatal | D14: =D2*inputs!$E$7*inputs!$E$8 -> 103647.91 | E14: =_xlfn.FORMULATEXT(D14) -> =D2*inputs!$E$7*inputs!$E$8
A15: Mother impact | B15: Women with moderate depression | C15: Number women moderately depressed postnatal | D15: =D3*inputs!E11*inputs!E12 -> 103212.71 | E15: =_xlfn.FORMULATEXT(D15) -> =D3*inputs!E11*inputs!E12
A16: Mother impact | B16: Women with moderate depression | C16: Number women moderately depressed Year +1 | D16: =D4*inputs!$E$11*inputs!$E$12*inputs!$E$15 -> 5157.0229 | E16: =_xlfn.FORMULATEXT(D16) -> =D4*inputs!$E$11*inputs!$E$12*inputs!$E$15
A17: Mother impact | B17: Women with moderate depression | C17: Number women moderately depressed Year +2 | D17: =D5*inputs!$E$11*inputs!$E$12*inputs!$E$15 -> 5153.413 | E17: =_xlfn.FORMULATEXT(D17) -> =D5*inputs!$E$11*inputs!$E$12*inputs!$E$15
A18: Mother impact | B18: Women with moderate depression | C18: Number women moderately depressed Year +3 | D18: =D6*inputs!$E$11*inputs!$E$12*inputs!$E$15 -> 5149.8056 | E18: =_xlfn.FORMULATEXT(D18) -> =D6*inputs!$E$11*inputs!$E$12*inputs!$E$15
A19: Mother impact | B19: Women with moderate depression | C19: Number women moderately depressed Year +4 | D19: =D7*inputs!$E$11*inputs!$E$12*inputs!$E$15 -> 5146.2007 | E19: =_xlfn.FORMULATEXT(D19) -> =D7*inputs!$E$11*inputs!$E$12*inputs!$E$15
A20: Mother impact | B20: Women with moderate depression | C20: Number women moderately depressed Year +5 | D20: =D8*inputs!$E$11*inputs!$E$12*inputs!$E$15 -> 5142.5984 | E20: =_xlfn.FORMULATEXT(D20) -> =D8*inputs!$E$11*inputs!$E$12*inputs!$E$15
A21: Mother impact | B21: Women with moderate depression | C21: Number women moderately depressed Year +6 | D21: =D9*inputs!$E$11*inputs!$E$12*inputs!$E$15 -> 5138.9986 | E21: =_xlfn.FORMULATEXT(D21) -> =D9*inputs!$E$11*inputs!$E$12*inputs!$E$15
A22: Mother impact | B22: Women with moderate depression | C22: Number women moderately depressed Year +7 | D22: =D10*inputs!$E$11*inputs!$E$12*inputs!$E$15 -> 5135.4013 | E22: =_xlfn.FORMULATEXT(D22) -> =D10*inputs!$E$11*inputs!$E$12*inputs!$E$15
A23: Mother impact | B23: Women with moderate depression | C23: Number women moderately depressed Year +8 | D23: =D11*inputs!$E$11*inputs!$E$12*inputs!$E$15 -> 5131.8065 | E23: =_xlfn.FORMULATEXT(D23) -> =D11*inputs!$E$11*inputs!$E$12*inputs!$E$15
A24: Mother impact | B24: Women with moderate depression | C24: Number women moderately depressed Year +9 | D24: =D12*inputs!$E$11*inputs!$E$12*inputs!$E$15 -> 5128.2142 | E24: =_xlfn.FORMULATEXT(D24) -> =D12*inputs!$E$11*inputs!$E$12*inputs!$E$15
A25: Mother impact | B25: Women with moderate depression | C25: Number women moderately depressed Year +10 | D25: =D13*inputs!$E$11*inputs!$E$12*inputs!$E$15 -> 5124.6245 | E25: =_xlfn.FORMULATEXT(D25) -> =D13*inputs!$E$11*inputs!$E$12*inputs!$E$15
A26: Mother impact | B26: Women with severe depression | C26: Number women severely depressed antenatal | D26: =D2*inputs!E7*inputs!E9 -> 25911.977 | E26: =_xlfn.FORMULATEXT(D26) -> =D2*inputs!E7*inputs!E9
A27: Mother impact | B27: Women with severe depression | C27: Number women severly depressed postnatal | D27: =D3*inputs!E11*inputs!E13 -> 25803.177 | E27: =_xlfn.FORMULATEXT(D27) -> =D3*inputs!E11*inputs!E13
A28: Mother impact | B28: Women with severe depression | C28: Number women severly depressed Year +1 | D28: =D4*inputs!$E$11*inputs!$E$13*inputs!$E$15 -> 1289.2557 | E28: =_xlfn.FORMULATEXT(D28) -> =D4*inputs!$E$11*inputs!$E$13*inputs!$E$15
A29: Mother impact | B29: Women with severe depression | C29: Number women severly depressed Year +2 | D29: =D5*inputs!$E$11*inputs!$E$13*inputs!$E$15 -> 1288.3532 | E29: =_xlfn.FORMULATEXT(D29) -> =D5*inputs!$E$11*inputs!$E$13*inputs!$E$15
A30: Mother impact | B30: Women with severe depression | C30: Number women severly depressed Year +3 | D30: =D6*inputs!$E$11*inputs!$E$13*inputs!$E$15 -> 1287.4514 | E30: =_xlfn.FORMULATEXT(D30) -> =D6*inputs!$E$11*inputs!$E$13*inputs!$E$15
A31: Mother impact | B31: Women with severe depression | C31: Number women severly depressed Year +4 | D31: =D7*inputs!$E$11*inputs!$E$13*inputs!$E$15 -> 1286.5502 | E31: =_xlfn.FORMULATEXT(D31) -> =D7*inputs!$E$11*inputs!$E$13*inputs!$E$15
A32: Mother impact | B32: Women with severe depression | C32: Number women severly depressed Year +5 | D32: =D8*inputs!$E$11*inputs!$E$13*inputs!$E$15 -> 1285.6496 | E32: =_xlfn.FORMULATEXT(D32) -> =D8*inputs!$E$11*inputs!$E$13*inputs!$E$15
A33: Mother impact | B33: Women with severe depression | C33: Number women severly depressed Year +6 | D33: =D9*inputs!$E$11*inputs!$E$13*inputs!$E$15 -> 1284.7496 | E33: =_xlfn.FORMULATEXT(D33) -> =D9*inputs!$E$11*inputs!$E$13*inputs!$E$15
A34: Mother impact | B34: Women with severe depression | C34: Number women severly depressed Year +7 | D34: =D10*inputs!$E$11*inputs!$E$13*inputs!$E$15 -> 1283.8503 | E34: =_xlfn.FORMULATEXT(D34) -> =D10*inputs!$E$11*inputs!$E$13*inputs!$E$15
A35: Mother impact | B35: Women with severe depression | C35: Number women severly depressed Year +8 | D35: =D11*inputs!$E$11*inputs!$E$13*inputs!$E$15 -> 1282.9516 | E35: =_xlfn.FORMULATEXT(D35) -> =D11*inputs!$E$11*inputs!$E$13*inputs!$E$15
A36: Mother impact | B36: Women with severe depression | C36: Number women severly depressed Year +9 | D36: =D12*inputs!$E$11*inputs!$E$13*inputs!$E$15 -> 1282.0536 | E36: =_xlfn.FORMULATEXT(D36) -> =D12*inputs!$E$11*inputs!$E$13*inputs!$E$15
A37: Mother impact | B37: Women with severe depression | C37: Number women severly depressed Year +10 | D37: =D13*inputs!$E$11*inputs!$E$13*inputs!$E$15 -> 1281.1561 | E37: =_xlfn.FORMULATEXT(D37) -> =D13*inputs!$E$11*inputs!$E$13*inputs!$E$15
A38: Mother impact | B38: Women with anxiety | C38: Number women anxious antenatal | D38: =D2*inputs!E10 -> 22672.98 | E38: =_xlfn.FORMULATEXT(D38) -> =D2*inputs!E10
A39: Mother impact | B39: Women with anxiety | C39: Number women anxious postnatal | D39: =D3*inputs!E14 -> 64507.942 | E39: =_xlfn.FORMULATEXT(D39) -> =D3*inputs!E14
A40: Mother impact | B40: Women with anxiety | C40: Number women anxious Year +1 | D40: =D4*inputs!$E$14*inputs!$E$16 -> 3223.1393 | E40: =_xlfn.FORMULATEXT(D40) -> =D4*inputs!$E$14*inputs!$E$16
A41: Mother impact | B41: Women with anxiety | C41: Number women anxious Year +2 | D41: =D5*inputs!$E$14*inputs!$E$16 -> 3220.8831 | E41: =_xlfn.FORMULATEXT(D41) -> =D5*inputs!$E$14*inputs!$E$16
A42: Mother impact | B42: Women with anxiety | C42: Number women anxious Year +3 | D42: =D6*inputs!$E$14*inputs!$E$16 -> 3218.6285 | E42: =_xlfn.FORMULATEXT(D42) -> =D6*inputs!$E$14*inputs!$E$16
A43: Mother impact | B43: Women with anxiety | C43: Number women anxious Year +4 | D43: =D7*inputs!$E$14*inputs!$E$16 -> 3216.3755 | E43: =_xlfn.FORMULATEXT(D43) -> =D7*inputs!$E$14*inputs!$E$16
A44: Mother impact | B44: Women with anxiety | C44: Number women anxious Year +5 | D44: =D8*inputs!$E$14*inputs!$E$16 -> 3214.124 | E44: =_xlfn.FORMULATEXT(D44) -> =D8*inputs!$E$14*inputs!$E$16
A45: Mother impact | B45: Women with anxiety | C45: Number women anxious Year +6 | D45: =D9*inputs!$E$14*inputs!$E$16 -> 3211.8741 | E45: =_xlfn.FORMULATEXT(D45) -> =D9*inputs!$E$14*inputs!$E$16
A46: Mother impact | B46: Women with anxiety | C46: Number women anxious Year +7 | D46: =D10*inputs!$E$14*inputs!$E$16 -> 3209.6258 | E46: =_xlfn.FORMULATEXT(D46) -> =D10*inputs!$E$14*inputs!$E$16
A47: Mother impact | B47: Women with anxiety | C47: Number women anxious Year +8 | D47: =D11*inputs!$E$14*inputs!$E$16 -> 3207.3791 | E47: =_xlfn.FORMULATEXT(D47) -> =D11*inputs!$E$14*inputs!$E$16
A48: Mother impact | B48: Women with anxiety | C48: Number women anxious Year +9 | D48: =D12*inputs!$E$14*inputs!$E$16 -> 3205.1339 | E48: =_xlfn.FORMULATEXT(D48) -> =D12*inputs!$E$14*inputs!$E$16
A49: Mother impact | B49: Women with anxiety | C49: Number women anxious Year +10 | D49: =D13*inputs!$E$14*inputs!$E$16 -> 3202.8903 | E49: =_xlfn.FORMULATEXT(D49) -> =D13*inputs!$E$14*inputs!$E$16
A50: Mother impact | B50: Women committing suicide | C50: Number women committing suicide ante- and postnatal | D50: =inputs!E24*(D2+D3)/100000 -> 71.108336 | E50: =_xlfn.FORMULATEXT(D50) -> =inputs!E24*(D2+D3)/100000
A51: Mother impact | B51: DALYs discounted | C51: DALYs women moderately depresssed antenatal | D51: =(D14*inputs!E17*inputs!E18)/(inputs!E31^0) -> 10261.143 | E51: =_xlfn.FORMULATEXT(D51) -> =(D14*inputs!E17*inputs!E18)/(inputs!E31^0)
A52: Mother impact | B52: DALYs discounted | C52: DALYs women moderately depresssed postnatal | D52: =(D15*inputs!E17*inputs!E18)/(inputs!E31^1) -> 9920.4446 | E52: =_xlfn.FORMULATEXT(D52) -> =(D15*inputs!E17*inputs!E18)/(inputs!E31^1)
A53: Mother impact | B53: DALYs discounted | C53: DALYs women moderately depresssed Year +1 | D53: =(D16*inputs!$E$18)/(inputs!$E$31^2) -> 1924.9515 | E53: =_xlfn.FORMULATEXT(D53) -> =(D16*inputs!$E$18)/(inputs!$E$31^2)
A54: Mother impact | B54: DALYs discounted | C54: DALYs women moderately depresssed Year +2 | D54: =(D17*inputs!$E$18)/(inputs!$E$31^3) -> 1867.5768 | E54: =_xlfn.FORMULATEXT(D54) -> =(D17*inputs!$E$18)/(inputs!$E$31^3)
A55: Mother impact | B55: DALYs discounted | C55: DALYs women moderately depresssed Year +3 | D55: =(D18*inputs!$E$18)/(inputs!$E$31^4) -> 1811.9121 | E55: =_xlfn.FORMULATEXT(D55) -> =(D18*inputs!$E$18)/(inputs!$E$31^4)
A56: Mother impact | B56: DALYs discounted | C56: DALYs women moderately depresssed Year +4 | D56: =(D19*inputs!$E$18)/(inputs!$E$31^5) -> 1757.9066 | E56: =_xlfn.FORMULATEXT(D56) -> =(D19*inputs!$E$18)/(inputs!$E$31^5)
A57: Mother impact | B57: DALYs discounted | C57: DALYs women moderately depresssed Year +5 | D57: =(D20*inputs!$E$18)/(inputs!$E$31^6) -> 1705.5107 | E57: =_xlfn.FORMULATEXT(D57) -> =(D20*inputs!$E$18)/(inputs!$E$31^6)
A58: Mother impact | B58: DALYs discounted | C58: DALYs women moderately depresssed Year +6 | D58: =(D21*inputs!$E$18)/(inputs!$E$31^7) -> 1654.6765 | E58: =_xlfn.FORMULATEXT(D58) -> =(D21*inputs!$E$18)/(inputs!$E$31^7)
A59: Mother impact | B59: DALYs discounted | C59: DALYs women moderately depresssed Year +7 | D59: =(D22*inputs!$E$18)/(inputs!$E$31^8) -> 1605.3575 | E59: =_xlfn.FORMULATEXT(D59) -> =(D22*inputs!$E$18)/(inputs!$E$31^8)
A60: Mother impact | B60: DALYs discounted | C60: DALYs women moderately depresssed Year +8 | D60: =(D23*inputs!$E$18)/(inputs!$E$31^9) -> 1557.5085 | E60: =_xlfn.FORMULATEXT(D60) -> =(D23*inputs!$E$18)/(inputs!$E$31^9)
A61: Mother impact | B61: DALYs discounted | C61: DALYs women moderately depresssed Year +9 | D61: =(D24*inputs!$E$18)/(inputs!$E$31^10) -> 1511.0857 | E61: =_xlfn.FORMULATEXT(D61) -> =(D24*inputs!$E$18)/(inputs!$E$31^10)
A62: Mother impact | B62: DALYs discounted | C62: DALYs women moderately depresssed Year +10 | D62: =(D25*inputs!$E$18)/(inputs!$E$31^11) -> 1466.0466 | E62: =_xlfn.FORMULATEXT(D62) -> =(D25*inputs!$E$18)/(inputs!$E$31^11)
A63: Mother impact | B63: DALYs discounted | C63: DALYs women severely depresssed antenatal | D63: =D26*inputs!E17*inputs!E19 -> 4262.5202 | E63: =_xlfn.FORMULATEXT(D63) -> =D26*inputs!E17*inputs!E19
A64: Mother impact | B64: DALYs discounted | C64: DALYs women severely depresssed postnatal | D64: =(D27*inputs!E17*inputs!E19)/(inputs!E31^1) -> 4120.9928 | E64: =_xlfn.FORMULATEXT(D64) -> =(D27*inputs!E17*inputs!E19)/(inputs!E31^1)
A65: Mother impact | B65: DALYs discounted | C65: DALYs women severely depresssed Year +1 | D65: =(D28*inputs!$E$19)/(inputs!$E$31^2) -> 799.63264 | E65: =_xlfn.FORMULATEXT(D65) -> =(D28*inputs!$E$19)/(inputs!$E$31^2)
A66: Mother impact | B66: DALYs discounted | C66: DALYs women severely depresssed Year +2 | D66: =(D29*inputs!$E$19)/(inputs!$E$31^3) -> 775.79893 | E66: =_xlfn.FORMULATEXT(D66) -> =(D29*inputs!$E$19)/(inputs!$E$31^3)
A67: Mother impact | B67: DALYs discounted | C67: DALYs women severely depresssed Year +3 | D67: =(D30*inputs!$E$19)/(inputs!$E$31^4) -> 752.6756 | E67: =_xlfn.FORMULATEXT(D67) -> =(D30*inputs!$E$19)/(inputs!$E$31^4)
A68: Mother impact | B68: DALYs discounted | C68: DALYs women severely depresssed Year +4 | D68: =(D31*inputs!$E$19)/(inputs!$E$31^5) -> 730.24148 | E68: =_xlfn.FORMULATEXT(D68) -> =(D31*inputs!$E$19)/(inputs!$E$31^5)
A69: Mother impact | B69: DALYs discounted | C69: DALYs women severely depresssed Year +5 | D69: =(D32*inputs!$E$19)/(inputs!$E$31^6) -> 708.47603 | E69: =_xlfn.FORMULATEXT(D69) -> =(D32*inputs!$E$19)/(inputs!$E$31^6)
A70: Mother impact | B70: DALYs discounted | C70: DALYs women severely depresssed Year +6 | D70: =(D33*inputs!$E$19)/(inputs!$E$31^7) -> 687.35932 | E70: =_xlfn.FORMULATEXT(D70) -> =(D33*inputs!$E$19)/(inputs!$E$31^7)
A71: Mother impact | B71: DALYs discounted | C71: DALYs women severely depresssed Year +7 | D71: =(D34*inputs!$E$19)/(inputs!$E$31^8) -> 666.87201 | E71: =_xlfn.FORMULATEXT(D71) -> =(D34*inputs!$E$19)/(inputs!$E$31^8)
A72: Mother impact | B72: DALYs discounted | C72: DALYs women severely depresssed Year +8 | D72: =(D35*inputs!$E$19)/(inputs!$E$31^9) -> 646.99534 | E72: =_xlfn.FORMULATEXT(D72) -> =(D35*inputs!$E$19)/(inputs!$E$31^9)
A73: Mother impact | B73: DALYs discounted | C73: DALYs women severely depresssed Year +9 | D73: =(D36*inputs!$E$19)/(inputs!$E$31^10) -> 627.71111 | E73: =_xlfn.FORMULATEXT(D73) -> =(D36*inputs!$E$19)/(inputs!$E$31^10)
A74: Mother impact | B74: DALYs discounted | C74: DALYs women severely depresssed Year +10 | D74: =(D37*inputs!$E$19)/(inputs!$E$31^11) -> 609.00166 | E74: =_xlfn.FORMULATEXT(D74) -> =(D37*inputs!$E$19)/(inputs!$E$31^11)
A75: Mother impact | B75: DALYs discounted | C75: DALYs women anxious antenatal | D75: =D38*inputs!E17*inputs!E20 -> 753.87657 | E75: =_xlfn.FORMULATEXT(D75) -> =D38*inputs!E17*inputs!E20
A76: Mother impact | B76: DALYs discounted | C76: DALYs women anxious postnatal | D76: =(D39*inputs!E17*inputs!E20)/(inputs!E31^1) -> 2082.4166 | E76: =_xlfn.FORMULATEXT(D76) -> =(D39*inputs!E17*inputs!E20)/(inputs!E31^1)
A77: Mother impact | B77: DALYs discounted | C77: DALYs women anxious Year +1 | D77: =(D40*inputs!$E$20)/(inputs!$E$31^2) -> 404.06968 | E77: =_xlfn.FORMULATEXT(D77) -> =(D40*inputs!$E$20)/(inputs!$E$31^2)
A78: Mother impact | B78: DALYs discounted | C78: DALYs women anxious Year +2 | D78: =(D41*inputs!$E$20)/(inputs!$E$31^3) -> 392.02605 | E78: =_xlfn.FORMULATEXT(D78) -> =(D41*inputs!$E$20)/(inputs!$E$31^3)
A79: Mother impact | B79: DALYs discounted | C79: DALYs women anxious Year +3 | D79: =(D42*inputs!$E$20)/(inputs!$E$31^4) -> 380.34139 | E79: =_xlfn.FORMULATEXT(D79) -> =(D42*inputs!$E$20)/(inputs!$E$31^4)
A80: Mother impact | B80: DALYs discounted | C80: DALYs women anxious Year +4 | D80: =(D43*inputs!$E$20)/(inputs!$E$31^5) -> 369.00501 | E80: =_xlfn.FORMULATEXT(D80) -> =(D43*inputs!$E$20)/(inputs!$E$31^5)
A81: Mother impact | B81: DALYs discounted | C81: DALYs women anxious Year +5 | D81: =(D44*inputs!$E$20)/(inputs!$E$31^6) -> 358.00651 | E81: =_xlfn.FORMULATEXT(D81) -> =(D44*inputs!$E$20)/(inputs!$E$31^6)
A82: Mother impact | B82: DALYs discounted | C82: DALYs women anxious Year +6 | D82: =(D45*inputs!$E$20)/(inputs!$E$31^7) -> 347.33583 | E82: =_xlfn.FORMULATEXT(D82) -> =(D45*inputs!$E$20)/(inputs!$E$31^7)
A83: Mother impact | B83: DALYs discounted | C83: DALYs women anxious Year +7 | D83: =(D46*inputs!$E$20)/(inputs!$E$31^8) -> 336.9832 | E83: =_xlfn.FORMULATEXT(D83) -> =(D46*inputs!$E$20)/(inputs!$E$31^8)
A84: Mother impact | B84: DALYs discounted | C84: DALYs women anxious Year +8 | D84: =(D47*inputs!$E$20)/(inputs!$E$31^9) -> 326.93913 | E84: =_xlfn.FORMULATEXT(D84) -> =(D47*inputs!$E$20)/(inputs!$E$31^9)
A85: Mother impact | B85: DALYs discounted | C85: DALYs women anxious Year +9 | D85: =(D48*inputs!$E$20)/(inputs!$E$31^10) -> 317.19444 | E85: =_xlfn.FORMULATEXT(D85) -> =(D48*inputs!$E$20)/(inputs!$E$31^10)
A86: Mother impact | B86: DALYs discounted | C86: DALYs women anxious Year +10 | D86: =(D49*inputs!$E$20)/(inputs!$E$31^11) -> 307.7402 | E86: =_xlfn.FORMULATEXT(D86) -> =(D49*inputs!$E$20)/(inputs!$E$31^11)
A87: Mother impact | B87: DALYs discounted | C87: DALYs women committing suicide ante and postnatal | D87: =D50*inputs!E25 -> 4266.5002 | E87: =_xlfn.FORMULATEXT(D87) -> =D50*inputs!E25
A88: Mother impact | B88: DALYs in USD | C88: DALYs women moderately depresssed antenatal, in USD | D88: =D51*(inputs!$E$26*inputs!$E$27) -> 36796458 | E88: =_xlfn.FORMULATEXT(D88) -> =D51*(inputs!$E$26*inputs!$E$27)
A89: Mother impact | B89: DALYs in USD | C89: DALYs women moderately depresssed postnatal, in USD | D89: =D52*(inputs!$E$26*inputs!$E$27) -> 35574714 | E89: =_xlfn.FORMULATEXT(D89) -> =D52*(inputs!$E$26*inputs!$E$27)
A90: Mother impact | B90: DALYs in USD | C90: DALYs women moderately depresssed Year +1, in USD | D90: =D53*(inputs!$E$26*inputs!$E$27) -> 6902876.2 | E90: =_xlfn.FORMULATEXT(D90) -> =D53*(inputs!$E$26*inputs!$E$27)
A91: Mother impact | B91: DALYs in USD | C91: DALYs women moderately depresssed Year +2, in USD | D91: =D54*(inputs!$E$26*inputs!$E$27) -> 6697130.2 | E91: =_xlfn.FORMULATEXT(D91) -> =D54*(inputs!$E$26*inputs!$E$27)
A92: Mother impact | B92: DALYs in USD | C92: DALYs women moderately depresssed Year +3, in USD | D92: =D55*(inputs!$E$26*inputs!$E$27) -> 6497516.7 | E92: =_xlfn.FORMULATEXT(D92) -> =D55*(inputs!$E$26*inputs!$E$27)
A93: Mother impact | B93: DALYs in USD | C93: DALYs women moderately depresssed Year +4, in USD | D93: =D56*(inputs!$E$26*inputs!$E$27) -> 6303852.9 | E93: =_xlfn.FORMULATEXT(D93) -> =D56*(inputs!$E$26*inputs!$E$27)
A94: Mother impact | B94: DALYs in USD | C94: DALYs women moderately depresssed Year +5, in USD | D94: =D57*(inputs!$E$26*inputs!$E$27) -> 6115961.4 | E94: =_xlfn.FORMULATEXT(D94) -> =D57*(inputs!$E$26*inputs!$E$27)
A95: Mother impact | B95: DALYs in USD | C95: DALYs women moderately depresssed Year +6, in USD | D95: =D58*(inputs!$E$26*inputs!$E$27) -> 5933670.1 | E95: =_xlfn.FORMULATEXT(D95) -> =D58*(inputs!$E$26*inputs!$E$27)
A96: Mother impact | B96: DALYs in USD | C96: DALYs women moderately depresssed Year +7, in USD | D96: =D59*(inputs!$E$26*inputs!$E$27) -> 5756812.1 | E96: =_xlfn.FORMULATEXT(D96) -> =D59*(inputs!$E$26*inputs!$E$27)
A97: Mother impact | B97: DALYs in USD | C97: DALYs women moderately depresssed Year +8, in USD | D97: =D60*(inputs!$E$26*inputs!$E$27) -> 5585225.6 | E97: =_xlfn.FORMULATEXT(D97) -> =D60*(inputs!$E$26*inputs!$E$27)
A98: Mother impact | B98: DALYs in USD | C98: DALYs women moderately depresssed Year +9, in USD | D98: =D61*(inputs!$E$26*inputs!$E$27) -> 5418753.3 | E98: =_xlfn.FORMULATEXT(D98) -> =D61*(inputs!$E$26*inputs!$E$27)
A99: Mother impact | B99: DALYs in USD | C99: DALYs women moderately depresssed Year +10, in USD | D99: =D62*(inputs!$E$26*inputs!$E$27) -> 5257242.9 | E99: =_xlfn.FORMULATEXT(D99) -> =D62*(inputs!$E$26*inputs!$E$27)
... A123: Mother impact | B123: DALYs in USD | C123: DALYs women anxious Year +10, in USD | D123: =D86*(inputs!$E$26*inputs!$E$27) -> 1103556.4 | E123: =_xlfn.FORMULATEXT(D123) -> =D86*(inputs!$E$26*inputs!$E$27)
...

Sheet outputs
B2: Section | C2: Subsection | D2: Variable Name | E2: Formula
B4: DALY loss Mothers depression | C4: Mothers impact | D4: Mothers DALY loss mothers depression | E4: =SUM(computations!D51:D74) -> 52432.397
B5: DALY loss Mothers depression in USD | C5: Mothers impact | D5: Mothers DALY loss mothers depression in USD | E5: =SUM(computations!D88:D111) -> 1.8802258e+08
B6: DALY loss Mothers anxiety | C6: Mothers impact | D6: Mothers DALY loss mothers anxiety | E6: =SUM(computations!D75:D87) -> 10642.435
B7: DALY loss Mothers anxiety in USD | C7: Mothers impact | D7: Mothers DALY loss mothers anxiety in USD | E7: =SUM(computations!D112:D123) -> 22864101
B8: DALY loss Mothers suicide | C8: Mothers impact | D8: Mothers DALY loss mothers suicide | E8: =computations!D87 -> 4266.5002
B9: DALY loss Mothers suicide in USD | C9: Mothers impact | D9: Mothers DALY loss mothers suicide in USD | E9: =computations!D124 -> 15299670
B10: Income loss Mothers depression in USD | C10: Mothers impact | D10: Mothers income loss mothers depression in USD | E10: =SUM(computations!D125:D136) -> 6.8293735e+08
B11: Income loss Mothers anxiety in USD | C11: Mothers impact | D11: Mothers income loss mothers anxiety in USD | E11: =SUM(computations!D137:D148) -> 2.4811754e+08
B12: DALY loss Children | C12: Childrens impact | D12: Childrens DALY loss total | E12: =SUM(computations!D355:D499) -> 185152.88
B13: DALY loss Children | C13: Childrens impact | D13: Childrens DALY loss outcome 1
B14: DALY loss Children | C14: Childrens impact | D14: Childrens DALY loss outcome 2
B15: DALY loss Children | C15: Childrens impact | D15: Childrens DALY loss outcome 3
B16: DALY loss Children | C16: Childrens impact | D16: Childrens DALY loss outcome 4
B17: DALY loss Children | C17: Childrens impact | D17: Childrens DALY loss outcome 5
B18: DALY loss Children | C18: Childrens impact | D18: Childrens DALY loss outcome 6
B19: DALY loss Children | C19: Childrens impact | D19: Childrens DALY loss outcome 7
B20: DALY loss Children | C20: Childrens impact | D20: Childrens DALY loss outcome 8
B21: DALY loss Children | C21: Childrens impact | D21: Childrens DALY loss outcome 9
B22: DALY loss Children | C22: Childrens impact | D22: Childrens DALY loss outcome 10
B23: DALY loss Children | C23: Childrens impact | D23: Childrens DALY loss outcome 11
B24: DALY loss Children in USD | C24: Childrens impact | D24: Childrens DALY loss in USD total | E24: =SUM(computations!D500:D644) -> 6.6395823e+08 | G24: Mother's DALY
B25: DALY loss Children in USD | C25: Childrens impact | D25: Childrens DALY loss in USD outcome 1
B26: DALY loss Children in USD | C26: Childrens impact | D26: Childrens DALY loss in USD outcome 2
B27: DALY loss Children in USD | C27: Childrens impact | D27: Childrens DALY loss in USD outcome 3
B28: DALY loss Children in USD | C28: Childrens impact | D28: Childrens DALY loss in USD outcome 4
B29: DALY loss Children in USD | C29: Childrens impact | D29: Childrens DALY loss in USD outcome 5
B30: DALY loss Children in USD | C30: Childrens impact | D30: Childrens DALY loss in USD outcome 6
B31: DALY loss Children in USD | C31: Childrens impact | D31: Childrens DALY loss in USD outcome 7
B32: DALY loss Children in USD | C32: Childrens impact | D32: Childrens DALY loss in USD outcome 8
B33: DALY loss Children in USD | C33: Childrens impact | D33: Childrens DALY loss in USD outcome 9
B34: DALY loss Children in USD | C34: Childrens impact | D34: Childrens DALY loss in USD outcome 10
B35: DALY loss Children in USD | C35: Childrens impact | D35: Childrens DALY loss in USD outcome 11
B36: Income loss Children in USD | C36: Childrens impact | D36: Childrens income loss in USD total | E36: =SUM(computations!D645:D744) -> 2.1637171e+08 | G36: =E7+E5+E9 -> 2.2618635e+08
B37: Income loss Children in USD | C37: Childrens impact | D37: Childrens income loss in USD outcome 7
B38: Income loss Children in USD | C38: Childrens impact | D38: Childrens income loss in USD outcome 9
B39: Income loss Children in USD | C39: Childrens impact | D39: Childrens income loss in USD outcome 10
B40: Income loss Children in USD | C40: Childrens impact | D40: Childrens income loss in USD outcome 11
B41: Healthcare expenditure children | C41: Childrens impact | D41: Childrens healthcare cost Age 0 to 1 in USD | E41: =SUM(computations!D745:D751) -> 58438963 | G41: Mother's Income loss
B42: Total cost mothers | C42: Total cost mothers | D42: Total cost mothers | E42: =E5+E7+E9+E10+E11 -> 1.1572412e+09 | G42: =E10+E11 -> 9.3105489e+08
B43: Total cost children | C43: Total cost children | D43: Total cost children | E43: =E24+E36+E41 -> 9.387689e+08
B44: Total cost mothers | C44: Total cost mothers | D44: Total cost mothers, in billion | E44: =E42/1000000000 -> 1.1572412
B45: Total cost children | C45: Total cost children | D45: Total cost children, in billion | E45: =E43/1000000000 -> 0.9387689
B56: Total DALY loss Mothers in USD | E56: =SUM(E5+E7+E9)/1000000 -> 226.18635 | F56: Million Dollars
